LICENSE
README.md
setup.cfg
setup.py
openl3/__init__.py
openl3/__main__.py
openl3/cli.py
openl3/core.py
openl3/models.py
openl3/openl3_exceptions.py
openl3/openl3_warnings.py
openl3/version.py
openl3.egg-info/PKG-INFO
openl3.egg-info/SOURCES.txt
openl3.egg-info/dependency_links.txt
openl3.egg-info/entry_points.txt
openl3.egg-info/requires.txt
openl3.egg-info/top_level.txt
tests/test_cli.py
tests/test_core.py
tests/test_models.py
tests/test_regression.py