Metadata-Version: 2.1
Name: openl3
Version: 0.4.2
Summary: Deep audio and image embeddings, based on Look, Listen, and Learn approach
Home-page: https://github.com/marl/openl3
Author: Aurora Cramer, Ho-Hsiang Wu, Bea Steers, and Justin Salamon
Author-email: jtc440@nyu.edu
License: MIT
Project-URL: Source, https://github.com/marl/openl3
Project-URL: Tracker, https://github.com/marl/openl3/issues
Project-URL: Documentation, https://readthedocs.org/projects/openl3/
Keywords: deep audio embeddings machine listening learning tensorflow keras
Classifier: Development Status :: 3 - Alpha
Classifier: License :: OSI Approved :: MIT License
Classifier: Intended Audience :: Developers
Classifier: Intended Audience :: Science/Research
Classifier: Topic :: Multimedia :: Sound/Audio :: Analysis
Classifier: Programming Language :: Python :: 3
Classifier: Programming Language :: Python :: 3.6
Classifier: Programming Language :: Python :: 3.7
Classifier: Programming Language :: Python :: 3.8
Provides-Extra: docs
Provides-Extra: tests
License-File: LICENSE
